{"namedChunkGroups":{"polyfill":{"name":"polyfill","assets":[{"name":"webpack-runtime-70a6284314d749b18547.js","size":6340},{"name":"polyfill-cf034b799f01cf2d99c3.js","size":82627}],"filteredAssets":0,"assetsSize":88967,"filteredAuxiliaryAssets":2,"auxiliaryAssetsSize":223203},"app":{"name":"app","assets":[{"name":"webpack-runtime-70a6284314d749b18547.js","size":6340},{"name":"framework-abac559b8e11af2e17b2.js","size":128955},{"name":"app-6bc749e7e055daaf9463.js","size":71263}],"filteredAssets":0,"assetsSize":206558,"filteredAuxiliaryAssets":3,"auxiliaryAssetsSize":659645},"component---src-pages-404-js":{"name":"component---src-pages-404-js","assets":[{"name":"styles.e84dcd1caa0bae10b2b1.css","size":19998},{"name":"cb1608f2-cf44794eabefe8f91558.js","size":687952},{"name":"a9a7754c-f159602de9f7ef6c99fc.js","size":465891},{"name":"commons-120c118a708f57b3afa3.js","size":53595},{"name":"component---src-pages-404-js-44eaee598f57dc1af124.js","size":471}],"filteredAssets":0,"assetsSize":1227907,"filteredAuxiliaryAssets":4,"auxiliaryAssetsSize":1557526},"component---src-pages-fellowships-js":{"name":"component---src-pages-fellowships-js","assets":[{"name":"styles.e84dcd1caa0bae10b2b1.css","size":19998},{"name":"cb1608f2-cf44794eabefe8f91558.js","size":687952},{"name":"a9a7754c-f159602de9f7ef6c99fc.js","size":465891},{"name":"commons-120c118a708f57b3afa3.js","size":53595},{"name":"component---src-pages-fellowships-js-b3a837af3b4b151f2cd6.js","size":7063}],"filteredAssets":0,"assetsSize":1234499,"filteredAuxiliaryAssets":4,"auxiliaryAssetsSize":1564213},"component---src-pages-index-js":{"name":"component---src-pages-index-js","assets":[{"name":"styles.e84dcd1caa0bae10b2b1.css","size":19998},{"name":"cb1608f2-cf44794eabefe8f91558.js","size":687952},{"name":"a9a7754c-f159602de9f7ef6c99fc.js","size":465891},{"name":"commons-120c118a708f57b3afa3.js","size":53595},{"name":"component---src-pages-index-js-94b08a66b81a5178f5a9.js","size":1797}],"filteredAssets":0,"assetsSize":1229233,"filteredAuxiliaryAssets":4,"auxiliaryAssetsSize":1559033},"component---src-pages-internships-js":{"name":"component---src-pages-internships-js","assets":[{"name":"styles.e84dcd1caa0bae10b2b1.css","size":19998},{"name":"cb1608f2-cf44794eabefe8f91558.js","size":687952},{"name":"a9a7754c-f159602de9f7ef6c99fc.js","size":465891},{"name":"commons-120c118a708f57b3afa3.js","size":53595},{"name":"component---src-pages-internships-js-cab99c7e7e96a8c97936.js","size":1726}],"filteredAssets":0,"assetsSize":1229162,"filteredAuxiliaryAssets":4,"auxiliaryAssetsSize":1558861},"component---src-pages-opportunities-js":{"name":"component---src-pages-opportunities-js","assets":[{"name":"styles.e84dcd1caa0bae10b2b1.css","size":19998},{"name":"cb1608f2-cf44794eabefe8f91558.js","size":687952},{"name":"a9a7754c-f159602de9f7ef6c99fc.js","size":465891},{"name":"commons-120c118a708f57b3afa3.js","size":53595},{"name":"component---src-pages-opportunities-js-b2b3dc64164a18626137.js","size":967}],"filteredAssets":0,"assetsSize":1228403,"filteredAuxiliaryAssets":4,"auxiliaryAssetsSize":1558199},"component---src-pages-partner-with-us-js":{"name":"component---src-pages-partner-with-us-js","assets":[{"name":"styles.e84dcd1caa0bae10b2b1.css","size":19998},{"name":"cb1608f2-cf44794eabefe8f91558.js","size":687952},{"name":"a9a7754c-f159602de9f7ef6c99fc.js","size":465891},{"name":"commons-120c118a708f57b3afa3.js","size":53595},{"name":"component---src-pages-partner-with-us-js-04399ad28e7c2212b8e7.js","size":544}],"filteredAssets":0,"assetsSize":1227980,"filteredAuxiliaryAssets":4,"auxiliaryAssetsSize":1557678},"component---src-pages-people-js":{"name":"component---src-pages-people-js","assets":[{"name":"styles.e84dcd1caa0bae10b2b1.css","size":19998},{"name":"cb1608f2-cf44794eabefe8f91558.js","size":687952},{"name":"a9a7754c-f159602de9f7ef6c99fc.js","size":465891},{"name":"commons-120c118a708f57b3afa3.js","size":53595},{"name":"component---src-pages-people-js-c8772f29366ab39ac5f4.js","size":2137}],"filteredAssets":0,"assetsSize":1229573,"filteredAuxiliaryAssets":4,"auxiliaryAssetsSize":1563056},"component---src-pages-people-past-js":{"name":"component---src-pages-people-past-js","assets":[{"name":"styles.e84dcd1caa0bae10b2b1.css","size":19998},{"name":"cb1608f2-cf44794eabefe8f91558.js","size":687952},{"name":"a9a7754c-f159602de9f7ef6c99fc.js","size":465891},{"name":"commons-120c118a708f57b3afa3.js","size":53595},{"name":"component---src-pages-people-past-js-89d6c81709299956643f.js","size":1617}],"filteredAssets":0,"assetsSize":1229053,"filteredAuxiliaryAssets":4,"auxiliaryAssetsSize":1560993},"component---src-pages-values-js":{"name":"component---src-pages-values-js","assets":[{"name":"styles.e84dcd1caa0bae10b2b1.css","size":19998},{"name":"cb1608f2-cf44794eabefe8f91558.js","size":687952},{"name":"a9a7754c-f159602de9f7ef6c99fc.js","size":465891},{"name":"commons-120c118a708f57b3afa3.js","size":53595},{"name":"component---src-pages-values-js-c268099db8e3796de0a7.js","size":2605}],"filteredAssets":0,"assetsSize":1230041,"filteredAuxiliaryAssets":4,"auxiliaryAssetsSize":1559665},"component---src-pages-what-we-do-js":{"name":"component---src-pages-what-we-do-js","assets":[{"name":"styles.e84dcd1caa0bae10b2b1.css","size":19998},{"name":"cb1608f2-cf44794eabefe8f91558.js","size":687952},{"name":"a9a7754c-f159602de9f7ef6c99fc.js","size":465891},{"name":"commons-120c118a708f57b3afa3.js","size":53595},{"name":"component---src-pages-what-we-do-js-7df8477705472fef25ee.js","size":595}],"filteredAssets":0,"assetsSize":1228031,"filteredAuxiliaryAssets":4,"auxiliaryAssetsSize":1557734},"component---src-pages-writing-group-js":{"name":"component---src-pages-writing-group-js","assets":[{"name":"styles.e84dcd1caa0bae10b2b1.css","size":19998},{"name":"cb1608f2-cf44794eabefe8f91558.js","size":687952},{"name":"a9a7754c-f159602de9f7ef6c99fc.js","size":465891},{"name":"commons-120c118a708f57b3afa3.js","size":53595},{"name":"component---src-pages-writing-group-js-6b8a290ed91795467c88.js","size":1275}],"filteredAssets":0,"assetsSize":1228711,"filteredAuxiliaryAssets":4,"auxiliaryAssetsSize":1558498},"component---src-templates-dialogue-index-js":{"name":"component---src-templates-dialogue-index-js","assets":[{"name":"styles.e84dcd1caa0bae10b2b1.css","size":19998},{"name":"cb1608f2-cf44794eabefe8f91558.js","size":687952},{"name":"a9a7754c-f159602de9f7ef6c99fc.js","size":465891},{"name":"commons-120c118a708f57b3afa3.js","size":53595},{"name":"5139c566e0e175d42196cb6a904f07c017d647fe-78a72a0c2175adacd54d.js","size":16723},{"name":"component---src-templates-dialogue-index-js-0ffd5a104b8b4ffbcc54.js","size":2019}],"filteredAssets":0,"assetsSize":1246178,"filteredAuxiliaryAssets":5,"auxiliaryAssetsSize":1616367},"component---src-templates-dialogue-js":{"name":"component---src-templates-dialogue-js","assets":[{"name":"styles.e84dcd1caa0bae10b2b1.css","size":19998},{"name":"cb1608f2-cf44794eabefe8f91558.js","size":687952},{"name":"a9a7754c-f159602de9f7ef6c99fc.js","size":465891},{"name":"commons-120c118a708f57b3afa3.js","size":53595},{"name":"5139c566e0e175d42196cb6a904f07c017d647fe-78a72a0c2175adacd54d.js","size":16723},{"name":"component---src-templates-dialogue-js-36bb4aebba3bff4168ba.js","size":5601}],"filteredAssets":0,"assetsSize":1249760,"filteredAuxiliaryAssets":5,"auxiliaryAssetsSize":1622590},"component---src-templates-event-index-js":{"name":"component---src-templates-event-index-js","assets":[{"name":"styles.e84dcd1caa0bae10b2b1.css","size":19998},{"name":"cb1608f2-cf44794eabefe8f91558.js","size":687952},{"name":"a9a7754c-f159602de9f7ef6c99fc.js","size":465891},{"name":"commons-120c118a708f57b3afa3.js","size":53595},{"name":"5139c566e0e175d42196cb6a904f07c017d647fe-78a72a0c2175adacd54d.js","size":16723},{"name":"component---src-templates-event-index-js-eb8017fa8caf798ee521.js","size":2714}],"filteredAssets":0,"assetsSize":1246873,"filteredAuxiliaryAssets":5,"auxiliaryAssetsSize":1619084},"component---src-templates-event-js":{"name":"component---src-templates-event-js","assets":[{"name":"styles.e84dcd1caa0bae10b2b1.css","size":19998},{"name":"cb1608f2-cf44794eabefe8f91558.js","size":687952},{"name":"a9a7754c-f159602de9f7ef6c99fc.js","size":465891},{"name":"commons-120c118a708f57b3afa3.js","size":53595},{"name":"5139c566e0e175d42196cb6a904f07c017d647fe-78a72a0c2175adacd54d.js","size":16723},{"name":"component---src-templates-event-js-80ef67dac3328b6be82b.js","size":4770}],"filteredAssets":0,"assetsSize":1248929,"filteredAuxiliaryAssets":5,"auxiliaryAssetsSize":1621877},"component---src-templates-person-js":{"name":"component---src-templates-person-js","assets":[{"name":"styles.e84dcd1caa0bae10b2b1.css","size":19998},{"name":"cb1608f2-cf44794eabefe8f91558.js","size":687952},{"name":"a9a7754c-f159602de9f7ef6c99fc.js","size":465891},{"name":"commons-120c118a708f57b3afa3.js","size":53595},{"name":"component---src-templates-person-js-177d311c23334394052c.js","size":6917}],"filteredAssets":0,"assetsSize":1234353,"filteredAuxiliaryAssets":4,"auxiliaryAssetsSize":1580133},"component---src-templates-post-index-js":{"name":"component---src-templates-post-index-js","assets":[{"name":"styles.e84dcd1caa0bae10b2b1.css","size":19998},{"name":"cb1608f2-cf44794eabefe8f91558.js","size":687952},{"name":"a9a7754c-f159602de9f7ef6c99fc.js","size":465891},{"name":"commons-120c118a708f57b3afa3.js","size":53595},{"name":"component---src-templates-post-index-js-10198c0c0b5d27655050.js","size":6998}],"filteredAssets":0,"assetsSize":1234434,"filteredAuxiliaryAssets":4,"auxiliaryAssetsSize":1581112},"component---src-templates-post-js":{"name":"component---src-templates-post-js","assets":[{"name":"styles.e84dcd1caa0bae10b2b1.css","size":19998},{"name":"cb1608f2-cf44794eabefe8f91558.js","size":687952},{"name":"a9a7754c-f159602de9f7ef6c99fc.js","size":465891},{"name":"commons-120c118a708f57b3afa3.js","size":53595},{"name":"component---src-templates-post-js-ffb14c8cd5c480181bf6.js","size":762}],"filteredAssets":0,"assetsSize":1228198,"filteredAuxiliaryAssets":4,"auxiliaryAssetsSize":1558934},"component---src-templates-research-index-js":{"name":"component---src-templates-research-index-js","assets":[{"name":"styles.e84dcd1caa0bae10b2b1.css","size":19998},{"name":"cb1608f2-cf44794eabefe8f91558.js","size":687952},{"name":"a9a7754c-f159602de9f7ef6c99fc.js","size":465891},{"name":"commons-120c118a708f57b3afa3.js","size":53595},{"name":"component---src-templates-research-index-js-1d41de22303520e280fa.js","size":9617}],"filteredAssets":0,"assetsSize":1237053,"filteredAuxiliaryAssets":4,"auxiliaryAssetsSize":1587294},"component---src-templates-research-js":{"name":"component---src-templates-research-js","assets":[{"name":"styles.e84dcd1caa0bae10b2b1.css","size":19998},{"name":"cb1608f2-cf44794eabefe8f91558.js","size":687952},{"name":"a9a7754c-f159602de9f7ef6c99fc.js","size":465891},{"name":"commons-120c118a708f57b3afa3.js","size":53595},{"name":"5139c566e0e175d42196cb6a904f07c017d647fe-78a72a0c2175adacd54d.js","size":16723},{"name":"component---src-templates-research-js-c3c1f0828a9e48f9cddf.js","size":6010}],"filteredAssets":0,"assetsSize":1250169,"filteredAuxiliaryAssets":5,"auxiliaryAssetsSize":1624768}},"assetsByChunkName":{"polyfill":["webpack-runtime-70a6284314d749b18547.js","polyfill-cf034b799f01cf2d99c3.js"],"app":["webpack-runtime-70a6284314d749b18547.js","framework-abac559b8e11af2e17b2.js","app-6bc749e7e055daaf9463.js"],"component---src-pages-404-js":["styles.e84dcd1caa0bae10b2b1.css","cb1608f2-cf44794eabefe8f91558.js","a9a7754c-f159602de9f7ef6c99fc.js","commons-120c118a708f57b3afa3.js","component---src-pages-404-js-44eaee598f57dc1af124.js"],"component---src-pages-fellowships-js":["styles.e84dcd1caa0bae10b2b1.css","cb1608f2-cf44794eabefe8f91558.js","a9a7754c-f159602de9f7ef6c99fc.js","commons-120c118a708f57b3afa3.js","component---src-pages-fellowships-js-b3a837af3b4b151f2cd6.js"],"component---src-pages-index-js":["styles.e84dcd1caa0bae10b2b1.css","cb1608f2-cf44794eabefe8f91558.js","a9a7754c-f159602de9f7ef6c99fc.js","commons-120c118a708f57b3afa3.js","component---src-pages-index-js-94b08a66b81a5178f5a9.js"],"component---src-pages-internships-js":["styles.e84dcd1caa0bae10b2b1.css","cb1608f2-cf44794eabefe8f91558.js","a9a7754c-f159602de9f7ef6c99fc.js","commons-120c118a708f57b3afa3.js","component---src-pages-internships-js-cab99c7e7e96a8c97936.js"],"component---src-pages-opportunities-js":["styles.e84dcd1caa0bae10b2b1.css","cb1608f2-cf44794eabefe8f91558.js","a9a7754c-f159602de9f7ef6c99fc.js","commons-120c118a708f57b3afa3.js","component---src-pages-opportunities-js-b2b3dc64164a18626137.js"],"component---src-pages-partner-with-us-js":["styles.e84dcd1caa0bae10b2b1.css","cb1608f2-cf44794eabefe8f91558.js","a9a7754c-f159602de9f7ef6c99fc.js","commons-120c118a708f57b3afa3.js","component---src-pages-partner-with-us-js-04399ad28e7c2212b8e7.js"],"component---src-pages-people-js":["styles.e84dcd1caa0bae10b2b1.css","cb1608f2-cf44794eabefe8f91558.js","a9a7754c-f159602de9f7ef6c99fc.js","commons-120c118a708f57b3afa3.js","component---src-pages-people-js-c8772f29366ab39ac5f4.js"],"component---src-pages-people-past-js":["styles.e84dcd1caa0bae10b2b1.css","cb1608f2-cf44794eabefe8f91558.js","a9a7754c-f159602de9f7ef6c99fc.js","commons-120c118a708f57b3afa3.js","component---src-pages-people-past-js-89d6c81709299956643f.js"],"component---src-pages-values-js":["styles.e84dcd1caa0bae10b2b1.css","cb1608f2-cf44794eabefe8f91558.js","a9a7754c-f159602de9f7ef6c99fc.js","commons-120c118a708f57b3afa3.js","component---src-pages-values-js-c268099db8e3796de0a7.js"],"component---src-pages-what-we-do-js":["styles.e84dcd1caa0bae10b2b1.css","cb1608f2-cf44794eabefe8f91558.js","a9a7754c-f159602de9f7ef6c99fc.js","commons-120c118a708f57b3afa3.js","component---src-pages-what-we-do-js-7df8477705472fef25ee.js"],"component---src-pages-writing-group-js":["styles.e84dcd1caa0bae10b2b1.css","cb1608f2-cf44794eabefe8f91558.js","a9a7754c-f159602de9f7ef6c99fc.js","commons-120c118a708f57b3afa3.js","component---src-pages-writing-group-js-6b8a290ed91795467c88.js"],"component---src-templates-dialogue-index-js":["styles.e84dcd1caa0bae10b2b1.css","cb1608f2-cf44794eabefe8f91558.js","a9a7754c-f159602de9f7ef6c99fc.js","commons-120c118a708f57b3afa3.js","5139c566e0e175d42196cb6a904f07c017d647fe-78a72a0c2175adacd54d.js","component---src-templates-dialogue-index-js-0ffd5a104b8b4ffbcc54.js"],"component---src-templates-dialogue-js":["styles.e84dcd1caa0bae10b2b1.css","cb1608f2-cf44794eabefe8f91558.js","a9a7754c-f159602de9f7ef6c99fc.js","commons-120c118a708f57b3afa3.js","5139c566e0e175d42196cb6a904f07c017d647fe-78a72a0c2175adacd54d.js","component---src-templates-dialogue-js-36bb4aebba3bff4168ba.js"],"component---src-templates-event-index-js":["styles.e84dcd1caa0bae10b2b1.css","cb1608f2-cf44794eabefe8f91558.js","a9a7754c-f159602de9f7ef6c99fc.js","commons-120c118a708f57b3afa3.js","5139c566e0e175d42196cb6a904f07c017d647fe-78a72a0c2175adacd54d.js","component---src-templates-event-index-js-eb8017fa8caf798ee521.js"],"component---src-templates-event-js":["styles.e84dcd1caa0bae10b2b1.css","cb1608f2-cf44794eabefe8f91558.js","a9a7754c-f159602de9f7ef6c99fc.js","commons-120c118a708f57b3afa3.js","5139c566e0e175d42196cb6a904f07c017d647fe-78a72a0c2175adacd54d.js","component---src-templates-event-js-80ef67dac3328b6be82b.js"],"component---src-templates-person-js":["styles.e84dcd1caa0bae10b2b1.css","cb1608f2-cf44794eabefe8f91558.js","a9a7754c-f159602de9f7ef6c99fc.js","commons-120c118a708f57b3afa3.js","component---src-templates-person-js-177d311c23334394052c.js"],"component---src-templates-post-index-js":["styles.e84dcd1caa0bae10b2b1.css","cb1608f2-cf44794eabefe8f91558.js","a9a7754c-f159602de9f7ef6c99fc.js","commons-120c118a708f57b3afa3.js","component---src-templates-post-index-js-10198c0c0b5d27655050.js"],"component---src-templates-post-js":["styles.e84dcd1caa0bae10b2b1.css","cb1608f2-cf44794eabefe8f91558.js","a9a7754c-f159602de9f7ef6c99fc.js","commons-120c118a708f57b3afa3.js","component---src-templates-post-js-ffb14c8cd5c480181bf6.js"],"component---src-templates-research-index-js":["styles.e84dcd1caa0bae10b2b1.css","cb1608f2-cf44794eabefe8f91558.js","a9a7754c-f159602de9f7ef6c99fc.js","commons-120c118a708f57b3afa3.js","component---src-templates-research-index-js-1d41de22303520e280fa.js"],"component---src-templates-research-js":["styles.e84dcd1caa0bae10b2b1.css","cb1608f2-cf44794eabefe8f91558.js","a9a7754c-f159602de9f7ef6c99fc.js","commons-120c118a708f57b3afa3.js","5139c566e0e175d42196cb6a904f07c017d647fe-78a72a0c2175adacd54d.js","component---src-templates-research-js-c3c1f0828a9e48f9cddf.js"]},"childAssetsByChunkName":{}}